elastro/__init__.py
elastro/py.typed
elastro/advanced/__init__.py
elastro/advanced/aggregations.py
elastro/advanced/query_builder.py
elastro/advanced/scroll.py
elastro/cli/__init__.py
elastro/cli/cli.py
elastro/cli/commands/__init__.py
elastro/cli/commands/config.py
elastro/cli/commands/datastream.py
elastro/cli/commands/document.py
elastro/cli/commands/index.py
elastro/cli/commands/utils.py
elastro/config/__init__.py
elastro/config/defaults.py
elastro/config/loader.py
elastro/core/__init__.py
elastro/core/client.py
elastro/core/datastream.py
elastro/core/document.py
elastro/core/document_bulk.py
elastro/core/errors.py
elastro/core/index.py
elastro/core/validation.py
elastro/utils/__init__.py
elastro/utils/aliases.py
elastro/utils/health.py
elastro/utils/snapshots.py
elastro/utils/templates.py
elastro-0.1.5.dist-info/licenses/LICENSE
elastro-0.1.5.dist-info/METADATA
elastro-0.1.5.dist-info/WHEEL
elastro-0.1.5.dist-info/entry_points.txt
elastro-0.1.5.dist-info/top_level.txt
elastro-0.1.5.dist-info/RECORD
